[
  {
    "wallet": {
      "name": "Alby",
      "uri": "https://getalby.com/"
    },
    "scans_bip21": "yes",
    "recognizes_lightning": "yes",
    "creates_bip21": "no",
    "description": "",
    "notes": "",
    "credit": {
      "name": "@sbddesign",
      "uri": "https://github.com/sbddesign"
    }
  },
  {
    "wallet": {
      "name": "Binance",
      "uri": "https://www.binance.com/"
    },
    "scans_bip21": "",
    "recognizes_lightning": "",
    "creates_bip21": "",
    "description": "",
    "notes": ""
  },
  {
    "wallet": {
      "name": "BitcoinBeach",
      "uri": "https://galoy.io/"
    },
    "scans_bip21": "yes",
    "recognizes_lightning": "no",
    "creates_bip21": "no",
    "description": "",
    "notes": "",
    "issue_link": "https://github.com/GaloyMoney/galoy-mobile/issues/411",
    "credit": {
      "name": "@sbddesign",
      "uri": "https://github.com/sbddesign"
    }
  },
  {
    "wallet": {
      "name": "The Bitcoin Company",
      "uri": "https://thebitcoincompany.com/"
    },
    "scans_bip21": "yes",
    "recognizes_lightning": "yes",
    "creates_bip21": "no",
    "description": "",
    "notes": "",
    "credit": {
      "name": "@benthecarman",
      "uri": "https://github.com/benthecarman"
    }
  },
  {
    "wallet": {
      "name": "Bitnob",
      "uri": "https://bitnob.com/"
    },
    "scans_bip21": "yes",
    "recognizes_lightning": "yes",
    "creates_bip21": "yes",
    "description": "Scans BIP21 QR codes and recognises lightning addresses. Generates BIP21 QR code without lightning parameter",
    "notes": "",
    "issue_link": "",
    "credit": {
      "name": "@MichaelEjila",
      "uri": "https://github.com/MichaelEjila"
    }
  },
  {
    "wallet": {
      "name": "BitPay",
      "uri": "https://bitpay.com/"
    },
    "scans_bip21": "yes",
    "recognizes_lightning": "n/a",
    "creates_bip21": "no",
    "description": "",
    "notes": "",
    "credit": {
      "name": "@sbddesign",
      "uri": "https://github.com/sbddesign"
    }
  },
  {
    "wallet": {
      "name": "Blixt",
      "uri": "https://blixtwallet.github.io/"
    },
    "scans_bip21": "yes",
    "recognizes_lightning": "yes",
    "creates_bip21": "no",
    "description": "QR code is not a valid bitcoin lightning invoice",
    "notes": "",
    "credit": {
      "name": "@sbddesign",
      "uri": "https://github.com/sbddesign"
    }
  },
  {
    "wallet": {
      "name": "Blockstream Green",
      "uri": "https://blockstream.com/green/"
    },
    "scans_bip21": "yes",
    "recognizes_lightning": "n/a",
    "creates_bip21": "no",
    "description": "",
    "notes": "",
    "credit": {
      "name": "@john_zaprite",
      "uri": "https://twitter.com/john_zaprite"
    }
  },
  {
    "wallet": {
      "name": "Bluewallet",
      "uri": "https://bluewallet.io/"
    },
    "scans_bip21": "yes",
    "recognizes_lightning": "yes",
    "creates_bip21": "no",
    "description": "Asks me to select a wallet, and I can choose my lightning wallet or on-chain wallet.",
    "notes": "Note that Bluewallet has 2 scanning methods. You can select a wallet and then scan the QR, or you can scan the QR without selecting a wallet. If you choose the latter and scan a BIP21 QR with lightning param, then it will prompt you to select a wallet because it sees your on-chain and lightning wallet as both being valid choices for this payment.",
    "credit": {
      "name": "@sbddesign",
      "uri": "https://github.com/sbddesign"
    }
  },
  {
    "wallet": {
      "name": "Bottlepay",
      "uri": "https://bottlepay.com/"
    },
    "scans_bip21": "yes",
    "recognizes_lightning": "yes",
    "creates_bip21": "no",
    "description": "Takes user directly to lightning payment screen.",
    "notes": "",
    "credit": {
      "name": "@pete001, @tom-smith8",
      "uri": "https://github.com/sbddesign/bip21-site/pull/73"
    }
  },
  {
    "wallet": {
      "name": "Breez",
      "uri": "https://breez.technology/"
    },
    "scans_bip21": "yes",
    "recognizes_lightning": "yes",
    "creates_bip21": "no",
    "description": "",
    "notes": "",
    "credit": {
      "name": "@sbddesign",
      "uri": "https://github.com/sbddesign"
    }
  },
  {
    "wallet": {
      "name": "BTCPay Server",
      "uri": "https://btcpayserver.org/"
    },
    "scans_bip21": "yes",
    "recognizes_lightning": "n/a",
    "creates_bip21": "yes",
    "description": "The BTCPayServer back-office Wallet > Send page will scan BIP21 URIs; Send > Wallet is on-chain only, so lightning is N/A in this context. The POS or store front-end is capable of generating a BIP21 URI containing a BOLT11 invoice if the admin turns this feature on in the settings. Props to @bitkarrot for a previous testing attempt.",
    "notes": "",
    "credit": {
      "name": "@pavlenex, @bitkarrot",
      "uri": "https://github.com/sbddesign/bip21-site/issues/53"
    }
  },
  {
    "wallet": {
      "name": "Casa",
      "uri": "https://keys.casa/"
    },
    "scans_bip21": "yes",
    "recognizes_lightning": "n/a",
    "creates_bip21": "no",
    "description": "",
    "notes": "",
    "credit": {
      "name": "@sbddesign",
      "uri": "https://github.com/sbddesign"
    }
  },
  {
    "wallet": {
      "name": "CashApp",
      "uri": "https://cash.app/"
    },
    "scans_bip21": "yes",
    "recognizes_lightning": "yes",
    "creates_bip21": "yes",
    "description": "After the most recent update, I scanned a BIP21 QR and CashApp recognized the lightning invoice. When scanning a BIP21 QR with an expired invoice, it falls back to the on-chain address. When receiving, it generates a BIP21 QR by default.",
    "notes": "",
    "credit": {
      "name": "@sbddesign",
      "uri": "https://github.com/sbddesign"
    }
  },
  {
    "wallet": {
      "name": "Chaincase",
      "uri": "https://chaincase.app/"
    },
    "scans_bip21": "yes",
    "recognizes_lightning": "n/a",
    "creates_bip21": "no",
    "description": "Pulls in the entire string including the 'bitcoin:', but I think it sees it as an on-chain address",
    "notes": "",
    "credit": {
      "name": "@sbddesign",
      "uri": "https://github.com/sbddesign"
    }
  },
  {
    "wallet": {
      "name": "Chivo",
      "uri": "https://www.chivowallet.com/"
    },
    "scans_bip21": "yes",
    "recognizes_lightning": "no",
    "creates_bip21": "no",
    "description": "",
    "notes": "",
    "issue_link": "https://twitter.com/StephenDeLorme/status/1504253220041940996",
    "credit": {
      "name": "@jcarlolife",
      "uri": "https://twitter.com/jcarlolife"
    }
  },
  {
    "wallet": {
      "name": "Coinbase (Exchange)",
      "uri": "https://www.coinbase.com/"
    },
    "scans_bip21": "",
    "recognizes_lightning": "",
    "creates_bip21": "",
    "description": "",
    "notes": ""
  },
  {
    "wallet": {
      "name": "Coinbase (Wallet)",
      "uri": "https://www.coinbase.com/"
    },
    "scans_bip21": "yes",
    "recognizes_lightning": "n/a",
    "creates_bip21": "no",
    "description": "",
    "notes": "",
    "credit": {
      "name": "@moneyball",
      "uri": "https://github.com/moneyball"
    }
  },
  {
    "wallet": {
      "name": "Edge Wallet",
      "uri": "https://edge.app/"
    },
    "scans_bip21": "yes",
    "recognizes_lightning": "n/a",
    "creates_bip21": "no",
    "description": "Can decode the QRcode that contains a BIP21 URI with bolt11 and the external onchain fallback. The URI can also be pasted, the onchain address is detected and users can send",
    "notes": "",
    "credit": {
      "name": "@theDavidCoen",
      "uri": "https://github.com/theDavidCoen"
    }
  },
  {
    "wallet": {
      "name": "Electrum",
      "uri": "https://electrum.org/"
    },
    "scans_bip21": "",
    "recognizes_lightning": "",
    "creates_bip21": "",
    "description": "",
    "notes": ""
  },
  {
    "wallet": {
      "name": "Gemini",
      "uri": "https://www.gemini.com/"
    },
    "scans_bip21": "",
    "recognizes_lightning": "",
    "creates_bip21": "",
    "description": "",
    "notes": ""
  },
  {
    "wallet": {
      "name": "Hexa",
      "uri": "https://hexawallet.io/"
    },
    "scans_bip21": "yes",
    "recognizes_lightning": "n/a",
    "creates_bip21": "no",
    "description": "",
    "notes": "",
    "credit": {
      "name": "@antuz123",
      "uri": "https://github.com/antuz123"
    }
  },
  {
    "wallet": {
      "name": "Kraken / Kraken Pro",
      "uri": "https://www.kraken.com/"
    },
    "scans_bip21": "yes",
    "recognizes_lightning": "no",
    "creates_bip21": "yes",
    "description": "The website and mobile apps do support creating a BIP21 QR code for deposits, but not with a lightning param.",
    "notes": "",
    "credit": {
      "name": "@PierreRochard",
      "uri": "https://github.com/PierreRochard"
    }
  },
  {
    "wallet": {
      "name": "LNBits",
      "uri": "https://github.com/lnbits/lnbits"
    },
    "scans_bip21": "no",
    "recognizes_lightning": "no",
    "creates_bip21": "no",
    "description": "When scanning the QR, it gives the folling error: Malformed request: checksum is incorrect. 400 BAD_REQUEST",
    "notes": "",
    "issue_link": "https://github.com/lnbits/lnbits/issues/1202",
    "credit": {
      "name": "@mutatrum",
      "uri": "https://github.com/mutatrum"
    }
  },  
  {
    "wallet": {
      "name": "Muun",
      "uri": "https://muun.com/"
    },
    "scans_bip21": "yes",
    "recognizes_lightning": "yes",
    "creates_bip21": "yes",
    "description": "Go to Settings > Lightning Network > Receiving protocol and set it to\"Unified\" to enable this feature",
    "notes": "",
    "credit": {
      "name": "@sbddesign",
      "uri": "https://github.com/sbddesign"
    }
  },
  {
    "wallet": {
      "name": "Nunchuk",
      "uri": "https://nunchuk.io/"
    },
    "scans_bip21": "yes",
    "recognizes_lightning": "n/a",
    "creates_bip21": "no",
    "description": "",
    "notes": "On-chain only, does not generate BIP21 addresses",
    "issue_link": "https://github.com/nunchuk-io/nunchuk-desktop/issues/10",
    "credit": {
      "name": "@bosch",
      "uri": "https://github.com/Bosch-0"
    }
  },
  {
    "wallet": {
      "name": "OKCoin",
      "uri": "https://www.okcoin.com/"
    },
    "scans_bip21": "",
    "recognizes_lightning": "",
    "creates_bip21": "",
    "description": "",
    "notes": ""
  },
  {
    "wallet": {
      "name": "OpenNode",
      "uri": "https://www.opennode.com/"
    },
    "scans_bip21": "n/a",
    "recognizes_lightning": "n/a",
    "creates_bip21": "yes",
    "description": "OpenNode is a Lightning Payment Provider that allows merchants to accept bitcoin. For developers, they provide an API to generate and manage generic \"charges\" that can be paid over either a bitcoin transaction or a lightning invoice. The charges API response object includes a `uri` field which contains a BIP21 URI + BOLT11 invoice.",
    "notes": "",
    "credit": {
      "name": "@alexlwn123",
      "uri": "https://github.com/alexlwn123"
    }
  },
  {
    "wallet": {
      "name": "Phoenix",
      "uri": "https://phoenix.acinq.co/"
    },
    "scans_bip21": "yes",
    "recognizes_lightning": "yes",
    "creates_bip21": "no",
    "description": "",
    "notes": "",
    "credit": {
      "name": "@sbddesign",
      "uri": "https://github.com/sbddesign"
    }
  },
  {
    "wallet": {
      "name": "River",
      "uri": "https://river.com/"
    },
    "scans_bip21": "yes",
    "recognizes_lightning": "no",
    "creates_bip21": "no",
    "description": "",
    "notes": "",
    "credit": {
      "name": "@bruteforcecat",
      "uri": "https://github.com/bruteforcecat"
    }
  },
  {
    "wallet": {
      "name": "Samourai",
      "uri": "https://samouraiwallet.com/"
    },
    "scans_bip21": "yes",
    "recognizes_lightning": "n/a",
    "creates_bip21": "no",
    "description": "",
    "notes": "",
    "credit": {
      "name": "@bosch",
      "uri": "https://github.com/Bosch-0"
    }
  },
  {
    "wallet": {
      "name": "Simple Bitcoin Wallet",
      "uri": ""
    },
    "scans_bip21": "yes",
    "recognizes_lightning": "yes",
    "creates_bip21": "",
    "description": "Needed a channel open to test but seemed to read the invoice.",
    "notes": "",
    "credit": {
      "name": "@bosch",
      "uri": "https://github.com/Bosch-0"
    }
  },
  {
    "wallet": {
      "name": "Strike",
      "uri": "https://strike.me/"
    },
    "scans_bip21": "yes",
    "recognizes_lightning": "yes",
    "creates_bip21": "no",
    "description": "Strike has been updated to recognize the lightning param after scanning",
    "notes": "",
    "issue_link": "",
    "credit": {
      "name": "@sbddesign, manuela, verbiricha",
      "uri": "https://github.com/sbddesign/bip21-site/pull/72#issue-1387877559"
    }
  },
  {
    "wallet": {
      "name": "Wallet of Satoshi",
      "uri": "https://www.walletofsatoshi.com/"
    },
    "scans_bip21": "yes",
    "recognizes_lightning": "yes",
    "creates_bip21": "no",
    "description": "",
    "notes": "",
    "credit": {
      "name": "@john_zaprite",
      "uri": "https://twitter.com/john_zaprite"
      }
},
  {
    "wallet": {
      "name": "Zap",
      "uri": "https://zaphq.io/"
    },
    "scans_bip21": "yes",
    "recognizes_lightning": "yes",
    "creates_bip21": "no",
    "description": "Zap defaults to on-chain if the included invoice is expired, but it recognizes Lightning when the invoice is still valid.",
    "issue_link": "https://github.com/LN-Zap/zap-android/pull/273",
    "notes": "",
    "credit": {
      "name": "@velaia",
      "uri": "https://github.com/velaia"
    }
  },
  {
    "wallet": {
      "name": "Zebedee",
      "uri": "https://zebedee.io/"
    },
    "scans_bip21": "no",
    "recognizes_lightning": "no",
    "creates_bip21": "no",
    "description": "This looks like an on-chain QR code...",
    "notes": "",
    "credit": {
      "name": "@sbddesign",
      "uri": "https://github.com/sbddesign"
    }
  },
  {
    "wallet": {
      "name": "Zeus",
      "uri": "https://zeusln.app/"
    },
    "scans_bip21": "yes",
    "recognizes_lightning": "no",
    "creates_bip21": "no",
    "description": "",
    "notes": "",
    "issue_link": "https://github.com/ZeusLN/zeus/issues/879",
    "credit": {
      "name": "@bosch",
      "uri": "https://github.com/Bosch-0"
    }
  }
]
